twine/__init__.py
twine/__main__.py
twine/auth.py
twine/cli.py
twine/exceptions.py
twine/package.py
twine/py.typed
twine/repository.py
twine/settings.py
twine/utils.py
twine/wheel.py
twine/wininst.py
twine/commands/__init__.py
twine/commands/check.py
twine/commands/register.py
twine/commands/upload.py
twine-6.0.0.dist-info/LICENSE
twine-6.0.0.dist-info/METADATA
twine-6.0.0.dist-info/WHEEL
twine-6.0.0.dist-info/entry_points.txt
twine-6.0.0.dist-info/top_level.txt
twine-6.0.0.dist-info/RECORD
