Metadata-Version: 2.1
Name: twine
Version: 6.0.0
Summary: Collection of utilities for publishing packages on PyPI
Author-email: Donald Stufft and individual contributors <donald@stufft.io>
Project-URL: Homepage, https://twine.readthedocs.io/
Project-URL: Source, https://github.com/pypa/twine/
Project-URL: Documentation, https://twine.readthedocs.io/en/latest/
Project-URL: Packaging tutorial, https://packaging.python.org/tutorials/packaging-projects/
Classifier: Intended Audience :: Developers
Classifier: License :: OSI Approved :: Apache Software License
Classifier: Natural Language :: English
Classifier: Operating System :: MacOS :: MacOS X
Classifier: Operating System :: POSIX
Classifier: Operating System :: POSIX :: BSD
Classifier: Operating System :: POSIX :: Linux
Classifier: Operating System :: Microsoft :: Windows
Classifier: Programming Language :: Python
Classifier: Programming Language :: Python :: 3
Classifier: Programming Language :: Python :: 3 :: Only
Classifier: Programming Language :: Python :: 3.8
Classifier: Programming Language :: Python :: 3.9
Classifier: Programming Language :: Python :: 3.10
Classifier: Programming Language :: Python :: 3.11
Classifier: Programming Language :: Python :: 3.12
Classifier: Programming Language :: Python :: Implementation :: CPython
Requires-Python: >=3.8
License-File: LICENSE
Requires-Dist: pkginfo>=1.8.1
Requires-Dist: readme-renderer>=35.0
Requires-Dist: requests>=2.20
Requires-Dist: requests-toolbelt!=0.9.0,>=0.8.0
Requires-Dist: urllib3>=1.26.0
Requires-Dist: importlib-metadata>=3.6
Requires-Dist: keyring>=15.1; platform_machine != "ppc64le" and platform_machine != "s390x"
Requires-Dist: rfc3986>=1.4.0
Requires-Dist: rich>=12.0.0
Requires-Dist: packaging
Provides-Extra: keyring
Requires-Dist: keyring>=15.1; extra == "keyring"
